flashtool/__init__.py
flashtool/autoscript.py
flashtool/emailutils.py
flashtool/logger.py
flashtool/pytorchutils.py
flashtool/time_profile.py
flashtool/trackjob.py
flashtool-0.0.10.dist-info/LICENSE
flashtool-0.0.10.dist-info/METADATA
flashtool-0.0.10.dist-info/WHEEL
flashtool-0.0.10.dist-info/top_level.txt
flashtool-0.0.10.dist-info/RECORD
