Metadata-Version: 2.1
Name: flashtool
Version: 0.0.10
Summary: A few ready-to use python tools for machine learning
Home-page: https://github.com/Gatech-Flash/FlashPythonToolbox
Author: Haoming Jiang
Author-email: jianghm.ustc@gmail.com
License: UNKNOWN
Platform: UNKNOWN
Classifier: Programming Language :: Python :: 3
Classifier: License :: OSI Approved :: MIT License
Classifier: Operating System :: OS Independent
Requires-Python: >=3.0
